frenchnlp/__init__.py
frenchnlp/sentence.py
frenchnlp/utils_xo.py
fummytransformers/__init__.py
fummytransformers/check_diff.py
fummytransformers/check_pickles.py
fummytransformers/data.py
fummytransformers/files.py
fummytransformers/gec.py
fummytransformers/performance.py
fummytransformers/sentence.py
fummytransformers/stat.py
fummytransformers/test.py
fummytransformers/test_1pickle.py
fummytransformers/test_delete.py
fummytransformers/test_filter.py
fummytransformers/test_pmi2.py
fummytransformers/test_regex.py
fummytransformers/test_svd.py
fummytransformers/transform.py
fummytransformers/utils.py
fummytransformers/utils_xo_others.py
sphinxext/__init__.py
sphinxext/custom_roles.py
sphinxext/gallery_order.py
sphinxext/github.py
sphinxext/math_symbol_table.py
sphinxext/missing_references.py
sphinxext/mock_gui_toolkits.py
sphinxext/redirect_from.py
sphinxext/skip_deprecated.py
sphinxext/numpydoc/__init__.py
sphinxext/numpydoc/__main__.py
sphinxext/numpydoc/docscrape.py
sphinxext/numpydoc/docscrape_sphinx.py
sphinxext/numpydoc/numpydoc.py
sphinxext/numpydoc/validate.py
sphinxext/numpydoc/xref.py
fummytransformers-0.0.18.dist-info/METADATA
fummytransformers-0.0.18.dist-info/WHEEL
fummytransformers-0.0.18.dist-info/top_level.txt
fummytransformers-0.0.18.dist-info/RECORD
