Metadata-Version: 2.1
Name: fummytransformers
Version: 0.0.18
Summary: Fast and dummy way of using transformers to establish quick baselines
Home-page: https://github.com/xiaoouwang/fummytransformers
Download-URL: https://pypi.org/project/fummytransformers
Author: Xiaoou WANG
Author-email: xiaoouwangfrance@gmail.com
License: Apache Licence 2.0
Keywords: text mining,npl,corpus,french,bert,transformers
Platform: UNKNOWN
Classifier: Programming Language :: Python :: 3
Classifier: License :: OSI Approved :: MIT License
Classifier: Operating System :: OS Independent
Requires-Dist: numpy
Requires-Dist: pandas
Requires-Dist: transformers
Requires-Dist: torch
Requires-Dist: py7zr
Requires-Dist: sklearn
Requires-Dist: tensorflow
